llama/Config.py
llama/Filters.py
llama/LlamaApi.py
llama/LlamaStats.py
llama/ProgSnap2.py
llama/__init__.py
llama/__main__.py
llama/anonymize.py
llama/exclude.py
llama/fetch.py
llama/list.py
llama/operations.py
llama/plotting.py
llama/privacy.py
llama/shell.py
llama/sources.py
llama/status.py
llama/common/__init__.py
llama/common/dataframes.py
llama/common/files.py
llama/common/input.py
llama/common/series.py
llama/types/AbstractApi.py
llama/types/AbstractDjangoApi.py
llama/types/AcosJsonApi.py
llama/types/AplusApi.py
llama/types/MongodumpApi.py
llama/types/__init__.py
llama/types/acosjson.py
llama/types/aplus.py
llama/types/mongodump.py
llama_cli-1.0.18.dist-info/LICENSE
llama_cli-1.0.18.dist-info/METADATA
llama_cli-1.0.18.dist-info/WHEEL
llama_cli-1.0.18.dist-info/entry_points.txt
llama_cli-1.0.18.dist-info/top_level.txt
llama_cli-1.0.18.dist-info/RECORD
