Metadata-Version: 2.1
Name: llama-cli
Version: 1.0.18
Summary: Llama CLI fetches and preprocesses learning data
Home-page: https://github.com/teemulehtinen/llama-cli
Author: Teemu Lehtinen
Author-email: teemu.t.lehtinen@aalto.fi
Classifier: Programming Language :: Python :: 3
Classifier: License :: OSI Approved :: MIT License
Classifier: Operating System :: OS Independent
Requires-Python: >=3.6
License-File: LICENSE
Requires-Dist: pandas
Requires-Dist: scipy
Requires-Dist: matplotlib
Requires-Dist: requests
